FinanceDataReader/__init__.py
FinanceDataReader/_utils.py
FinanceDataReader/chart.py
FinanceDataReader/data.py
FinanceDataReader/data2.py
FinanceDataReader/setup.py
FinanceDataReader/fred/__init__.py
FinanceDataReader/fred/data.py
FinanceDataReader/investing/__init__.py
FinanceDataReader/investing/data.py
FinanceDataReader/investing/listing.py
FinanceDataReader/investing/listing2.py
FinanceDataReader/krx/__init__.py
FinanceDataReader/krx/data.py
FinanceDataReader/krx/listing.py
FinanceDataReader/krx/listing2.py
FinanceDataReader/nasdaq/__init__.py
FinanceDataReader/nasdaq/listing.py
FinanceDataReader/naver/__init__.py
FinanceDataReader/naver/data.py
FinanceDataReader/naver/listing.py
FinanceDataReader/naver/listing2.py
FinanceDataReader/wikipedia/__init__.py
FinanceDataReader/wikipedia/listing.py
FinanceDataReader/yahoo/__init__.py
FinanceDataReader/yahoo/data.py
finance_datareader_HSB-0.2.7.dist-info/METADATA
finance_datareader_HSB-0.2.7.dist-info/WHEEL
finance_datareader_HSB-0.2.7.dist-info/top_level.txt
finance_datareader_HSB-0.2.7.dist-info/RECORD
